pyhilite
