Metadata-Version: 1.1
Name: pyhilite
Version: 0.2.0
Summary: Python3 binding of GNU source-highlight C++ library
Home-page: UNKNOWN
Author: Wiky L
Author-email: wiiiky@outlook.com
License: GPLv3
Keywords: Source Code,Highlight,HTML,Latex
Platform: UNKNOWN
Classifier: Development Status :: 3 - Alpha
Classifier: Intended Audience :: Developers
Classifier: License :: OSI Approved :: GNU Lesser General Public License v3 or later (LGPLv3+)
Classifier: Operating System :: POSIX :: Linux
Classifier: Programming Language :: Python
